machinae/__init__.py
machinae/cmd.py
machinae/outputs.py
machinae/utils.py
machinae/sites/__init__.py
machinae/sites/base.py
machinae/sites/csv.py
machinae/sites/html.py
machinae/sites/ipwhois.py
machinae/sites/json.py
machinae/sites/rss.py
machinae-1.4.11.dist-info/LICENSE.txt
machinae-1.4.11.dist-info/METADATA
machinae-1.4.11.dist-info/WHEEL
machinae-1.4.11.dist-info/entry_points.txt
machinae-1.4.11.dist-info/top_level.txt
machinae-1.4.11.dist-info/RECORD
