Metadata-Version: 2.1
Name: machinae
Version: 1.4.11
Summary: Machinae Security Intelligence Collector
Home-page: http://hurricanelabs.github.io/machinae/
Author: Steve McMaster
Author-email: mcmaster@hurricanelabs.com
Classifier: License :: OSI Approved :: MIT License
Classifier: Programming Language :: Python :: 3 :: Only
Classifier: Development Status :: 5 - Production/Stable
License-File: LICENSE.txt
Requires-Dist: dnspython3
Requires-Dist: ipwhois <0.11
Requires-Dist: requests
Requires-Dist: stopit
Requires-Dist: pyyaml
Requires-Dist: beautifulsoup4
Requires-Dist: html5lib
Requires-Dist: relatime
Requires-Dist: tzlocal
Requires-Dist: python-magic
Requires-Dist: feedparser
Requires-Dist: defang
